setup.cfg
setup.py
jsonclient/__init__.py
jsonclient/backend.py
jsonclient/cached.py
jsonclient/mako_render_tools.py
jsonclient/messages.py
jsonclient/renderers.py
jsonclient/routing.py
jsonclient/test.py
jsonclientHGMMP.egg-info/PKG-INFO
jsonclientHGMMP.egg-info/SOURCES.txt
jsonclientHGMMP.egg-info/dependency_links.txt
jsonclientHGMMP.egg-info/not-zip-safe
jsonclientHGMMP.egg-info/requires.txt
jsonclientHGMMP.egg-info/top_level.txt