Metadata-Version: 1.0
Name: jsonclientHGMMP
Version: 0.0.3
Summary: Mapping JSON to objects and vice versa, this is a product of Christopher Lenz and Matthew Good with slight modifications
Home-page: https://github.com
Author: Martin Peschke
Author-email: martin@per-4.com
License: BSD
Platform: UNKNOWN
